{
  "extension": {
    "variations": [
      {
        "country": "México",
        "dateCreated": "2010-12-23T20:02:34.501004",
        "extNumber": "1457",
        "id": 2,
        "intNumber": "pisos 7 al 14",
        "state": "CDMX",
        "street": "Avenida Insurgentes Sur",
        "suburb": "Colonia Insurgentes Mixcoac",
        "township": "Alcaldía Benito Juárez",
        "version": "1"
      },
      {
        "country": "México",
        "dateCreated": "2010-12-23T20:02:34.758009",
        "extNumber": "1457",
        "id": 3,
        "intNumber": "piso 11",
        "state": "CDMX",
        "street": "Avenida Insurgentes Sur",
        "suburb": "Colonia Insurgentes Mixcoac",
        "township": "Alcaldía Benito Juárez",
        "version": "1"
      },
      {
        "country": "México",
        "dateCreated": "2010-12-23T20:02:34.969603",
        "extNumber": "1457",
        "id": 5,
        "intNumber": "piso 11",
        "state": "CDMX",
        "street": "Avenida Insurgentes Sur",
        "suburb": "Colonia Insurgentes Mixcoac",
        "township": "Alcaldía Benito Juárez",
        "version": "1"
      },
      {
        "country": "México",
        "dateCreated": "2010-12-23T20:02:35.079111",
        "extNumber": "1457",
        "id": 6,
        "intNumber": "piso 11",
        "state": "CDMX",
        "street": "Avenida Insurgentes Sur",
        "suburb": "Colonia Insurgentes Mixcoac",
        "township": "Alcaldía Benito Juárez",
        "version": "1"
      },
      {
        "country": "México",
        "dateCreated": "2010-12-23T20:02:35.1915",
        "extNumber": "1457",
        "id": 7,
        "intNumber": "piso 11",
        "state": "CDMX",
        "street": "Avenida Insurgentes Sur",
        "suburb": "Colonia Insurgentes Mixcoac",
        "township": "Alcaldía Benito Juárez",
        "version": "1"
      },
      {
        "country": "México",
        "dateCreated": "2010-12-23T20:02:35.301452",
        "extNumber": "1457",
        "id": 8,
        "intNumber": "piso 11",
        "state": "CDMX",
        "street": "Avenida Insurgentes Sur",
        "suburb": "Colonia Insurgentes Mixcoac",
        "township": "Alcaldía Benito Juárez",
        "version": "1"
      },
      {
        "country": "México",
        "dateCreated": "2010-12-23T20:02:35.417368",
        "extNumber": "90 Torre 1",
        "id": 9,
        "intNumber": "Piso 11 Oficina B",
        "location": "Cuajimalpa de Morelos",
        "state": "Ciudad de México",
        "street": "Avenida Paseo de los Tamarindos",
        "suburb": "Bosques de las Lomas",
        "township": "Cuajimalpa de Morelos",
        "version": "1"
      },
      {
        "country": "México",
        "dateCreated": "2010-12-23T20:02:35.52865",
        "extNumber": "1457",
        "id": 10,
        "intNumber": "piso 11",
        "state": "DMX",
        "street": "Avenida Insurgentes Sur",
        "suburb": "Colonia Insurgentes Mixcoac",
        "township": "Alcaldía Benito Juárez",
        "version": "1"
      },
      {
        "country": "México",
        "dateCreated": "2012-06-23T00:00:00",
        "extNumber": "120 Oriente",
        "id": 11,
        "location": "San Pedro Garza García",
        "state": "Nuevo León",
        "street": "Calzada del Valle",
        "suburb": "Del Valle",
        "township": "San Pedro Garza García",
        "version": "1"
      },
      {
        "country": "México",
        "dateCreated": "2012-06-23T00:00:00",
        "extNumber": "1677 PH 1",
        "id": 12,
        "intNumber": "Sector Juárez",
        "location": "Guadalajara",
        "state": "Jalisco",
        "street": "Pedro Moreno",
        "suburb": "Americana",
        "township": "Guadalajara",
        "version": "1"
      },
      {
        "country": "México",
        "dateCreated": "2012-06-27T00:00:00",
        "extNumber": "265 PB",
        "id": 13,
        "location": "Cuauhtémoc",
        "state": "CDMX",
        "street": "Paseo de la Reforma",
        "suburb": "Cuauhtémoc",
        "township": "Cuauhtémoc",
        "version": "1"
      },
      {
        "country": "México",
        "dateCreated": "2012-06-23T00:00:00",
        "extNumber": "10 PB",
        "id": 14,
        "location": "Cuauhtémoc",
        "state": "CDMX",
        "street": "Tonala",
        "suburb": "Roma",
        "township": "Cuauhtémoc",
        "version": "1"
      },
      {
        "country": "México",
        "dateCreated": "2012-06-27T00:00:00",
        "extNumber": "1738",
        "id": 15,
        "location": "Álvaro Obregón",
        "state": "CDMX",
        "street": "Av. Insurgentes Sur",
        "suburb": "Florida",
        "township": "Álvaro Obregón",
        "version": "1"
      },
      {
        "country": "México",
        "dateCreated": "2012-10-22T16:24:06.185007",
        "extNumber": "56",
        "id": 739,
        "intNumber": "Piso 5",
        "state": "CDMX",
        "street": "Bosque de Ciruelos",
        "suburb": "Bosques de las Lomas",
        "township": "Miguel Hidalgo",
        "version": "1"
      },
      {
        "country": "México",
        "dateCreated": "2013-12-09T12:27:48.04272",
        "extNumber": "1457",
        "id": 839,
        "intNumber": "piso 11",
        "state": "CDMX",
        "street": "Avenida Insurgentes Sur",
        "suburb": "Colonia Insurgentes Mixcoac",
        "township": "Alcaldía Benito Juárez",
        "version": "1"
      },
      {
        "country": "México",
        "dateCreated": "2013-12-09T12:34:50.774",
        "extNumber": "1457",
        "id": 841,
        "intNumber": "piso 11",
        "state": "CDMX",
        "street": "Avenida Insurgentes Sur",
        "suburb": "Colonia Insurgentes Mixcoac",
        "township": "Alcaldía Benito Juárez",
        "version": "1"
      },
      {
        "country": "México",
        "dateCreated": "2014-02-22T11:01:29.881",
        "extNumber": "1457",
        "id": 860,
        "intNumber": "Piso 11",
        "state": "CDMX",
        "street": "Avenida Insurgentes Sur",
        "suburb": "Colonia Insurgentes Mixcoac",
        "township": "Alcaldía Benito Juárez",
        "version": "1"
      },
      {
        "country": "México",
        "dateCreated": "2014-02-22T12:58:01.254419",
        "extNumber": "1457",
        "id": 861,
        "intNumber": "piso 11",
        "state": "CDMX",
        "street": "Avenida Insurgentes Sur",
        "suburb": "Colonia Insurgentes Mixcoac",
        "township": "Alcaldía Benito Juárez",
        "version": "1"
      },
      {
        "country": "México",
        "dateCreated": "2019-06-18T13:11:32.114932",
        "extNumber": "1351",
        "id": 1487,
        "location": "Queretaro",
        "state": "Queretaro",
        "street": "Av. 5 de Febrero",
        "suburb": "Industrial Benito Juárez",
        "township": "Queretaro",
        "version": "1"
      },
      {
        "country": "México",
        "dateCreated": "2019-06-18T13:14:50.327",
        "extNumber": "1351",
        "id": 1489,
        "location": "Queretaro",
        "state": "Queretaro",
        "street": "Av. 5 de Febrero",
        "suburb": "Industrial Benito Juárez",
        "township": "Queretaro",
        "version": "1"
      }
    ]
  }
}
